RanjeetTrial/Ex_Zeus.py
RanjeetTrial/Ex_Zeus1.py
RanjeetTrial/Ex_Zeus_Defs.py
RanjeetTrial/Ex_Zeus_Logs.py
RanjeetTrial/__init__.py
RanjeetTrial/main.py
RanjeetTrial/nikhil.py
ranjeettrial-0.0.6.dist-info/licenses/LICENSE
ranjeettrial-0.0.6.dist-info/METADATA
ranjeettrial-0.0.6.dist-info/WHEEL
ranjeettrial-0.0.6.dist-info/top_level.txt
ranjeettrial-0.0.6.dist-info/RECORD
