Metadata-Version: 2.4
Name: RanjeetTrial
Version: 0.0.6
Summary: Just for trial - convert CSV/TSV to XLSX
Author: Ranjeet Aloriya
License: MIT
Classifier: Programming Language :: Python :: 3
Classifier: License :: OSI Approved :: MIT License
Classifier: Operating System :: OS Independent
Requires-Python: >=3.7
License-File: LICENSE
Requires-Dist: pandas
Requires-Dist: openpyxl
Requires-Dist: xlrd
Requires-Dist: xlsxwriter
Requires-Dist: polars
Requires-Dist: numpy
Requires-Dist: networkx
Requires-Dist: tqdm
Dynamic: license-file
